[
	{
		"name": "Faded",
		"artist": "Alan Walker",
		"url": "https://jenly1314.github.io/musics/Faded.mp3",
		"cover": "https://jenly1314.github.io/musics/Faded.jpg"
	},
	{
		"name": "Love To Be Loved By You",
		"artist": "Marc Terenzi",
		"url": "https://jenly1314.github.io/musics/LoveToBeLovedByYou.mp3",
		"cover": "https://jenly1314.github.io/musics/LoveToBeLovedByYou.jpg"
	},
	{
		"name": "Take me hand",
		"artist": "DAISHI DANCE / Cecile Corbel",
		"url": "https://jenly1314.github.io/musics/TakeMeHand.mp3",
		"cover": "https://jenly1314.github.io/musics/TakeMeHand.jpg"
	},
	{
		"name": "Something Just Like This",
		"artist": "The Chainsmokers / Coldplay",
		"url": "https://jenly1314.github.io/musics/SomethingJustLikeThis.mp3",
		"cover": "https://jenly1314.github.io/musics/SomethingJustLikeThis.jpg"
	},
	{
		"name": "That Girl",
		"artist": "Olly Murs",
		"url": "https://jenly1314.github.io/musics/ThatGirl.mp3",
		"cover": "https://jenly1314.github.io/musics/ThatGirl.jpg"
	},
	{
		"name": "Legends Never Die",
		"artist": "Against the Current",
		"url": "https://jenly1314.github.io/musics/LegendsNeverDie.mp3",
		"cover": "https://jenly1314.github.io/musics/LegendsNeverDie.jpg"
	}
]